{
    "id": "gu3qmPeDfwsQ70r",
    "url": "https://www.amazon.com/dp/B07984JN3L?_encoding=UTF8&ie=UTF-8&plattr=ACOMFO",
    "loadedUrl": "https://www.amazon.com/dp/B07984JN3L?_encoding=UTF8&ie=UTF-8&plattr=ACOMFO",
    "uniqueKey": "https://www.amazon.com/dp/B07984JN3L?_encoding=UTF8&ie=UTF-8&plattr=ACOMFO",
    "method": "GET",
    "payload": null,
    "noRetry": false,
    "retryCount": 0,
    "errorMessages": null,
    "headers": {},
    "userData": {},
    "handledAt": "2020-05-19T07:28:46.539Z"
}