{
    "url": "https://www.amazon.com/gp/customer-preferences/select-language/ref=topnav_lang_t1?preferencesReturnUrl=%2Fgp%2Fhelp%2Fcustomer%2Fdisplay.html%2Fref%3Dicp_flyout%3Fie%3DUTF8%26nodeId%3D202085910",
    "loadedUrl": null,
    "uniqueKey": "https://www.amazon.com/gp/customer-preferences/select-language/ref=topnav_lang_t1?preferencesReturnUrl=%2Fgp%2Fhelp%2Fcustomer%2Fdisplay.html%2Fref%3Dicp_flyout%3Fie%3DUTF8%26nodeId%3D202085910",
    "method": "GET",
    "payload": null,
    "noRetry": false,
    "retryCount": 0,
    "errorMessages": null,
    "headers": {},
    "userData": {},
    "handledAt": null,
    "id": "nX0vXAjMcB7zB63"
}