{
    "url": "https://www.amazon.com/gp/redirect.html?location=https%3A%2F%2Fsell.amazon.com%2F%3Fld%3DAZFSSOA-m%26ref_%3Dfooter_soa_m&source=nav_linktree&token=EF9FF32530CB33AC7C35D159E66652C44A80C2B3",
    "loadedUrl": null,
    "uniqueKey": "https://www.amazon.com/gp/redirect.html?location=https%3A%2F%2Fsell.amazon.com%2F%3Fld%3DAZFSSOA-m%26ref_%3Dfooter_soa_m&source=nav_linktree&token=EF9FF32530CB33AC7C35D159E66652C44A80C2B3",
    "method": "GET",
    "payload": null,
    "noRetry": false,
    "retryCount": 0,
    "errorMessages": null,
    "headers": {},
    "userData": {},
    "handledAt": null,
    "id": "KJICX1pIs6xRK8s"
}