{
    "url": "https://www.amazon.com/gp/redirect.html/ref=mh_s9_acss_cg_vassf_1d1_w?location=http://go.amazonsellerservices.com/applytosellservicessoa1a&token=7C0E7EC37BC26703292B6FBCF6F833A21EBA338D&source=standards&pf_rd_m=ATVPDKIKX0DER&pf_rd_s=mobile-hybrid-12&pf_rd_r=H3RPE58DZ0YG036DH8AF&pf_rd_t=1201&pf_rd_p=952123dc-fa83-4849-a840-3885eb58ddd9&pf_rd_i=8098158011",
    "loadedUrl": null,
    "uniqueKey": "https://www.amazon.com/gp/redirect.html/ref=mh_s9_acss_cg_vassf_1d1_w?location=http://go.amazonsellerservices.com/applytosellservicessoa1a&pf_rd_i=8098158011&pf_rd_m=ATVPDKIKX0DER&pf_rd_p=952123dc-fa83-4849-a840-3885eb58ddd9&pf_rd_r=H3RPE58DZ0YG036DH8AF&pf_rd_s=mobile-hybrid-12&pf_rd_t=1201&source=standards&token=7C0E7EC37BC26703292B6FBCF6F833A21EBA338D",
    "method": "GET",
    "payload": null,
    "noRetry": false,
    "retryCount": 0,
    "errorMessages": null,
    "headers": {},
    "userData": {},
    "handledAt": null,
    "id": "z3mpNgWk1gufeII"
}